{
  "station": 3339,
  "type": "sj",
  "startYear": 2024,
  "nYears": 3,
  "quant": {
    "temp": 10,
    "wind": 10,
    "precip": 1,
    "dv": 1
  },
  "cols": {
    "t": [
      null,
      null,
      null,
      null,
      null,
      null,
      null,
      null,
      null,
      null,
      null,
      null,
      null,
      null,
      null,
      null,
      null,
      null,
      null,
      null,
      null,
      null,
      null,
      null,
      null,
      null,
      null,
      null,
      null,
      null,
      null,
      null,
      null,
      null,
      null,
      null,
      null,
      null,
      null,
      null,
      null,
      null,
      null,
      null,
      null,
      null,
      null,
      null,
      null,
      null,
      null,
      null,
      null,
      null,
      null,
      null,
      null,
      null,
      null,
      null,
      null,
      null,
      null,
      null,
      null,
      null,
      null,
      null,
      null,
      null,
      null,
      null,
      null,
      null,
      null,
      null,
      null,
      null,
      null,
      null,
      null,
      null,
      null,
      null,
      null,
      null,
      null,
      null,
      null,
      null,
      null,
      null,
      null,
      null,
      null,
      null,
      null,
      null,
      null,
      null,
      null,
      null,
      null,
      null,
      null,
      null,
      null,
      null,
      null,
      null,
      null,
      null,
      null,
      null,
      null,
      null,
      null,
      null,
      null,
      null,
      null,
      null,
      null,
      null,
      null,
      null,
      null,
      null,
      null,
      null,
      null,
      null,
      null,
      null,
      null,
      null,
      null,
      null,
      null,
      null,
      null,
      null,
      null,
      null,
      null,
      null,
      null,
      null,
      null,
      null,
      null,
      null,
      null,
      null,
      null,
      null,
      null,
      null,
      null,
      null,
      null,
      null,
      null,
      null,
      null,
      null,
      null,
      null,
      null,
      null,
      null,
      null,
      null,
      null,
      null,
      null,
      null,
      null,
      null,
      null,
      null,
      null,
      null,
      null,
      null,
      null,
      null,
      null,
      null,
      null,
      null,
      null,
      null,
      null,
      null,
      null,
      null,
      null,
      null,
      null,
      null,
      null,
      null,
      null,
      null,
      null,
      null,
      null,
      null,
      null,
      null,
      null,
      null,
      null,
      null,
      null,
      null,
      null,
      null,
      null,
      null,
      null,
      null,
      null,
      null,
      null,
      null,
      null,
      null,
      null,
      null,
      null,
      null,
      null,
      null,
      null,
      null,
      null,
      null,
      null,
      null,
      null,
      null,
      null,
      null,
      null,
      101,
      143,
      111,
      108,
      47,
      20,
      32,
      41,
      18,
      21,
      10,
      44,
      20,
      78,
      56,
      60,
      52,
      62,
      27,
      5,
      29,
      18,
      14,
      26,
      15,
      26,
      8,
      80,
      84,
      42,
      -10,
      -14,
      -18,
      -30,
      -16,
      -24,
      -6,
      -37,
      -40,
      -76,
      -96,
      -36,
      9,
      -2,
      10,
      67,
      26,
      8,
      -25,
      -11,
      -1,
      19,
      23,
      -35,
      28,
      34,
      24,
      -16,
      -23,
      -20,
      59,
      85,
      110,
      52,
      80,
      53,
      114,
      83,
      100,
      96,
      68,
      98,
      -10,
      -24,
      -106,
      -152,
      -112,
      -100,
      -168,
      -194,
      -180,
      -82,
      -90,
      23,
      29,
      -87,
      -139,
      -57,
      -98,
      -99,
      13,
      -12,
      -16,
      -28,
      -45,
      61,
      68,
      13,
      15,
      28,
      -35,
      13,
      -31,
      -44,
      -2,
      -32,
      -43,
      4,
      -37,
      -46,
      24,
      7,
      -28,
      6,
      6,
      -24,
      -92,
      -152,
      -171,
      -102,
      -37,
      -73,
      -144,
      -99,
      -50,
      -102,
      -148,
      -74,
      11,
      41,
      49,
      19,
      79,
      74,
      32,
      -28,
      -6,
      -6,
      5,
      -46,
      -36,
      8,
      -3,
      -22,
      -24,
      -82,
      -82,
      -67,
      -10,
      17,
      67,
      18,
      20,
      -4,
      20,
      36,
      16,
      -7,
      44,
      69,
      9,
      11,
      19,
      -31,
      -26,
      -37,
      -24,
      -8,
      6,
      14,
      39,
      5,
      5,
      -1,
      -18,
      -19,
      11,
      42,
      23,
      21,
      3,
      4,
      -7,
      -12,
      -4,
      -36,
      -10,
      39,
      28,
      24,
      23,
      42,
      45,
      56,
      65,
      67,
      63,
      63,
      34,
      28,
      19,
      0,
      55,
      23,
      5,
      -17,
      -24,
      -21,
      39,
      31,
      10,
      30,
      51,
      73,
      86,
      93,
      90,
      96,
      105,
      39,
      36,
      4,
      9,
      24,
      21,
      -1,
      18,
      30,
      21,
      11,
      14,
      15,
      39,
      58,
      90,
      57,
      52,
      75,
      69,
      63,
      51,
      86,
      107,
      97,
      104,
      106,
      74,
      39,
      43,
      56,
      96,
      128,
      127,
      158,
      125,
      168,
      156,
      139,
      99,
      140,
      150,
      122,
      79,
      79,
      85,
      82,
      86,
      81,
      80,
      81,
      76,
      45,
      31,
      47,
      30,
      19,
      40,
      49,
      63,
      74,
      94,
      92,
      77,
      87,
      83,
      86,
      103,
      108,
      104,
      111,
      130,
      129,
      112,
      115,
      119,
      111,
      109,
      94,
      68,
      55,
      72,
      104,
      122,
      121,
      134,
      116,
      141,
      144,
      143,
      132,
      136,
      114,
      151,
      130,
      118,
      148,
      139,
      119,
      121,
      130,
      134,
      141,
      143,
      148,
      136,
      101,
      86,
      131,
      144,
      132,
      110,
      115,
      147,
      134,
      119,
      127,
      126,
      107,
      77,
      89,
      82,
      96,
      106,
      92,
      101,
      130,
      162,
      141,
      101,
      127,
      71,
      98,
      83,
      159,
      157,
      139,
      155,
      163,
      140,
      103,
      104,
      98,
      120,
      101,
      86,
      90,
      95,
      82,
      56,
      96,
      99,
      90,
      130,
      82,
      63,
      112,
      97,
      83,
      28,
      28,
      17,
      23,
      55,
      88,
      115,
      110,
      102,
      114,
      92,
      45,
      53,
      107,
      92,
      93,
      68,
      38,
      72,
      49,
      17,
      45,
      62,
      69,
      84,
      115,
      102,
      129,
      101,
      49,
      65,
      39,
      24,
      10,
      -7,
      -12,
      -34,
      -8,
      -46,
      -61,
      -99,
      -76,
      -98,
      -88,
      2,
      62,
      38,
      34,
      21,
      -9,
      -31,
      -36,
      16,
      3,
      8,
      -82,
      -100,
      -50,
      -11,
      2,
      -54,
      -26,
      -118,
      -36,
      26,
      32,
      -6,
      -46,
      -50,
      13,
      12,
      -33,
      -63,
      -96,
      -29,
      null,
      null,
      null,
      null,
      null,
      null,
      null,
      null,
      null,
      null,
      null,
      54,
      12,
      -43,
      -43,
      -69,
      -18,
      1,
      -54,
      -13,
      15,
      40,
      46,
      93,
      94,
      34,
      29,
      51,
      10,
      42,
      -5,
      -35,
      -110,
      -107,
      -47,
      -46,
      -118,
      -149,
      -40,
      -120,
      -119,
      -89,
      -22,
      -34,
      -67,
      -107,
      9,
      -16,
      50,
      40,
      -9,
      -12,
      83,
      52,
      -21,
      -34,
      -22,
      2,
      -30,
      -68,
      -81,
      -91,
      -87,
      -18,
      -13,
      -40,
      -58,
      -20,
      -77,
      -48,
      14,
      -32,
      -137,
      -115,
      -103,
      -149,
      -153,
      -90,
      -176,
      -141,
      -90,
      -101,
      -99,
      -61,
      31,
      3,
      -31,
      17,
      -53,
      -24,
      -55,
      -36,
      -38,
      17,
      3,
      43,
      21,
      8,
      23,
      34,
      2,
      -9,
      -2,
      6,
      16,
      3,
      -3,
      0,
      39,
      -22,
      -20,
      -19,
      -19,
      -20,
      -56,
      -33,
      -5,
      -27,
      10,
      15,
      0,
      0,
      31,
      -7,
      -30,
      -25,
      9,
      74,
      61,
      52,
      28,
      5,
      28,
      28,
      22,
      43,
      63,
      63,
      32,
      45,
      74,
      74,
      78,
      70,
      54,
      59,
      83,
      108,
      109,
      67,
      50,
      5,
      29,
      23,
      0,
      4,
      7,
      3,
      -2,
      28,
      40,
      85,
      47,
      43,
      61,
      92,
      95,
      84,
      63,
      65,
      62,
      89,
      102,
      100,
      95,
      91,
      92,
      91,
      63,
      55,
      69,
      103,
      103,
      84,
      85,
      72,
      78,
      112,
      94,
      104,
      99,
      101,
      84,
      85,
      98,
      82,
      123,
      116,
      95,
      102,
      93,
      66,
      82,
      98,
      108,
      100,
      106,
      100,
      112,
      104,
      102,
      121,
      133,
      91,
      76,
      80,
      84,
      96,
      122,
      138,
      119,
      114,
      147,
      155,
      139,
      143,
      157,
      134,
      156,
      141,
      157,
      167,
      null,
      null,
      null,
      null,
      null,
      null,
      null,
      null,
      null,
      null,
      null,
      null,
      null,
      null,
      null,
      null,
      null,
      null,
      null,
      null,
      null,
      null,
      null,
      null,
      null,
      null,
      null,
      null,
      null,
      null,
      null,
      null,
      null,
      null,
      null,
      null,
      null,
      null,
      null,
      null,
      null,
      null,
      null,
      null,
      null,
      null,
      null,
      null,
      null,
      null,
      null,
      null,
      null,
      null,
      null,
      null,
      null,
      null,
      null,
      null,
      null,
      null,
      null,
      null,
      null,
      null,
      null,
      null,
      null,
      null,
      null,
      null,
      null,
      null,
      null,
      null,
      null,
      null,
      null,
      null,
      null,
      null,
      null,
      null,
      null,
      null,
      null,
      null,
      null,
      null,
      null,
      null,
      null,
      null,
      null,
      null,
      null,
      null,
      null,
      null,
      null,
      null,
      null,
      null,
      null,
      null,
      null,
      null,
      null,
      null,
      null,
      null,
      null,
      null,
      null,
      null,
      null,
      null,
      null,
      null,
      null,
      null,
      null,
      null,
      null,
      null,
      null,
      null,
      null,
      null,
      null,
      null,
      null,
      null,
      null,
      null,
      null,
      null,
      null,
      null,
      null,
      null,
      null,
      null,
      null,
      null,
      null,
      null,
      null,
      null,
      null,
      null,
      null,
      null,
      null,
      null,
      null,
      null,
      null,
      null,
      null,
      null,
      null,
      null
    ],
    "tx": [
      null,
      null,
      null,
      null,
      null,
      null,
      null,
      null,
      null,
      null,
      null,
      null,
      null,
      null,
      null,
      null,
      null,
      null,
      null,
      null,
      null,
      null,
      null,
      null,
      null,
      null,
      null,
      null,
      null,
      null,
      null,
      null,
      null,
      null,
      null,
      null,
      null,
      null,
      null,
      null,
      null,
      null,
      null,
      null,
      null,
      null,
      null,
      null,
      null,
      null,
      null,
      null,
      null,
      null,
      null,
      null,
      null,
      null,
      null,
      null,
      null,
      null,
      null,
      null,
      null,
      null,
      null,
      null,
      null,
      null,
      null,
      null,
      null,
      null,
      null,
      null,
      null,
      null,
      null,
      null,
      null,
      null,
      null,
      null,
      null,
      null,
      null,
      null,
      null,
      null,
      null,
      null,
      null,
      null,
      null,
      null,
      null,
      null,
      null,
      null,
      null,
      null,
      null,
      null,
      null,
      null,
      null,
      null,
      null,
      null,
      null,
      null,
      null,
      null,
      null,
      null,
      null,
      null,
      null,
      null,
      null,
      null,
      null,
      null,
      null,
      null,
      null,
      null,
      null,
      null,
      null,
      null,
      null,
      null,
      null,
      null,
      null,
      null,
      null,
      null,
      null,
      null,
      null,
      null,
      null,
      null,
      null,
      null,
      null,
      null,
      null,
      null,
      null,
      null,
      null,
      null,
      null,
      null,
      null,
      null,
      null,
      null,
      null,
      null,
      null,
      null,
      null,
      null,
      null,
      null,
      null,
      null,
      null,
      null,
      null,
      null,
      null,
      null,
      null,
      null,
      null,
      null,
      null,
      null,
      null,
      null,
      null,
      null,
      null,
      null,
      null,
      null,
      null,
      null,
      null,
      null,
      null,
      null,
      null,
      null,
      null,
      null,
      null,
      null,
      null,
      null,
      null,
      null,
      null,
      null,
      null,
      null,
      null,
      null,
      null,
      null,
      null,
      null,
      null,
      null,
      null,
      null,
      null,
      null,
      null,
      null,
      null,
      null,
      null,
      null,
      null,
      null,
      null,
      null,
      null,
      null,
      null,
      null,
      null,
      null,
      null,
      null,
      null,
      null,
      null,
      null,
      163,
      199,
      160,
      147,
      107,
      38,
      45,
      85,
      90,
      100,
      68,
      70,
      75,
      116,
      129,
      111,
      104,
      123,
      65,
      80,
      50,
      50,
      46,
      50,
      43,
      51,
      46,
      115,
      107,
      85,
      64,
      62,
      73,
      41,
      27,
      10,
      13,
      -3,
      -9,
      14,
      8,
      20,
      25,
      23,
      84,
      96,
      66,
      24,
      1,
      22,
      27,
      74,
      58,
      -9,
      87,
      64,
      45,
      30,
      31,
      30,
      126,
      136,
      136,
      136,
      129,
      104,
      151,
      139,
      173,
      153,
      81,
      139,
      28,
      -6,
      -37,
      -99,
      -53,
      -51,
      -92,
      -130,
      -143,
      -23,
      -28,
      59,
      56,
      -17,
      -124,
      -22,
      -50,
      21,
      41,
      31,
      1,
      -11,
      -20,
      119,
      123,
      44,
      94,
      61,
      -21,
      46,
      8,
      4,
      21,
      -4,
      -6,
      43,
      11,
      -15,
      57,
      33,
      -11,
      49,
      49,
      -9,
      -31,
      -100,
      -108,
      -79,
      -6,
      -26,
      -92,
      -39,
      -27,
      -54,
      -105,
      -6,
      45,
      61,
      96,
      74,
      110,
      103,
      81,
      -8,
      19,
      48,
      36,
      -5,
      -16,
      84,
      76,
      -11,
      -10,
      -44,
      -27,
      -29,
      42,
      109,
      121,
      46,
      59,
      23,
      72,
      106,
      43,
      35,
      77,
      84,
      63,
      68,
      57,
      17,
      19,
      38,
      15,
      28,
      47,
      42,
      83,
      18,
      51,
      14,
      3,
      12,
      40,
      77,
      65,
      73,
      21,
      57,
      11,
      23,
      28,
      5,
      41,
      65,
      79,
      60,
      67,
      80,
      74,
      101,
      88,
      87,
      98,
      94,
      65,
      54,
      54,
      50,
      80,
      43,
      44,
      17,
      20,
      -1,
      55,
      61,
      57,
      74,
      95,
      120,
      117,
      148,
      146,
      131,
      133,
      87,
      88,
      28,
      38,
      63,
      61,
      27,
      69,
      93,
      92,
      70,
      66,
      81,
      117,
      157,
      143,
      135,
      91,
      125,
      142,
      90,
      75,
      159,
      159,
      122,
      136,
      137,
      112,
      74,
      100,
      117,
      146,
      199,
      208,
      241,
      171,
      253,
      218,
      226,
      171,
      206,
      219,
      145,
      96,
      100,
      128,
      119,
      112,
      112,
      114,
      124,
      132,
      81,
      56,
      76,
      42,
      41,
      81,
      76,
      111,
      126,
      146,
      149,
      121,
      134,
      151,
      105,
      139,
      130,
      132,
      154,
      167,
      177,
      152,
      157,
      147,
      159,
      167,
      129,
      81,
      72,
      116,
      138,
      167,
      173,
      185,
      183,
      238,
      184,
      175,
      167,
      197,
      164,
      237,
      179,
      148,
      227,
      171,
      142,
      145,
      158,
      173,
      204,
      170,
      215,
      199,
      133,
      110,
      206,
      171,
      154,
      158,
      181,
      197,
      167,
      174,
      180,
      172,
      153,
      102,
      122,
      117,
      135,
      135,
      122,
      159,
      166,
      210,
      186,
      140,
      199,
      91,
      179,
      150,
      225,
      189,
      200,
      224,
      212,
      197,
      121,
      124,
      125,
      165,
      126,
      96,
      132,
      140,
      153,
      74,
      189,
      130,
      123,
      188,
      100,
      93,
      174,
      156,
      136,
      91,
      68,
      54,
      75,
      104,
      140,
      140,
      148,
      143,
      162,
      128,
      153,
      124,
      126,
      138,
      124,
      101,
      68,
      121,
      84,
      50,
      94,
      107,
      107,
      156,
      158,
      145,
      149,
      126,
      100,
      116,
      81,
      55,
      33,
      30,
      11,
      28,
      33,
      -10,
      -1,
      -40,
      -42,
      -25,
      -60,
      86,
      93,
      50,
      56,
      49,
      21,
      14,
      12,
      72,
      31,
      49,
      -32,
      -55,
      -1,
      13,
      36,
      4,
      17,
      -92,
      7,
      75,
      62,
      7,
      -24,
      -34,
      51,
      40,
      -1,
      -36,
      -29,
      37,
      null,
      null,
      null,
      null,
      null,
      null,
      null,
      null,
      null,
      null,
      null,
      94,
      58,
      -11,
      -21,
      -40,
      51,
      21,
      -14,
      27,
      51,
      86,
      75,
      111,
      116,
      94,
      83,
      87,
      44,
      64,
      67,
      -5,
      -59,
      -59,
      -23,
      -23,
      -74,
      -49,
      17,
      -41,
      -77,
      -14,
      -11,
      -21,
      -26,
      3,
      16,
      35,
      85,
      91,
      43,
      104,
      120,
      112,
      55,
      20,
      40,
      57,
      43,
      -16,
      -45,
      -39,
      -7,
      20,
      29,
      41,
      15,
      21,
      -9,
      12,
      33,
      24,
      -61,
      -50,
      -58,
      -97,
      -83,
      -52,
      -108,
      -49,
      -46,
      -34,
      -20,
      -5,
      66,
      66,
      12,
      64,
      -15,
      13,
      6,
      -9,
      82,
      65,
      32,
      84,
      49,
      36,
      76,
      70,
      18,
      4,
      10,
      29,
      44,
      44,
      11,
      41,
      84,
      20,
      8,
      1,
      21,
      5,
      -35,
      36,
      21,
      25,
      38,
      45,
      46,
      29,
      69,
      35,
      45,
      66,
      66,
      96,
      96,
      84,
      59,
      41,
      57,
      83,
      79,
      116,
      135,
      107,
      60,
      112,
      169,
      143,
      120,
      122,
      97,
      86,
      136,
      143,
      147,
      106,
      89,
      44,
      87,
      67,
      34,
      34,
      44,
      41,
      62,
      79,
      88,
      115,
      77,
      65,
      119,
      137,
      124,
      149,
      130,
      110,
      98,
      151,
      157,
      157,
      141,
      142,
      134,
      130,
      75,
      79,
      114,
      177,
      148,
      131,
      137,
      105,
      129,
      172,
      151,
      165,
      149,
      171,
      130,
      105,
      151,
      129,
      188,
      197,
      132,
      144,
      125,
      91,
      122,
      146,
      156,
      127,
      145,
      150,
      159,
      141,
      133,
      175,
      174,
      117,
      132,
      142,
      124,
      149,
      181,
      192,
      155,
      170,
      187,
      191,
      156,
      173,
      197,
      176,
      225,
      184,
      197,
      209,
      null,
      null,
      null,
      null,
      null,
      null,
      null,
      null,
      null,
      null,
      null,
      null,
      null,
      null,
      null,
      null,
      null,
      null,
      null,
      null,
      null,
      null,
      null,
      null,
      null,
      null,
      null,
      null,
      null,
      null,
      null,
      null,
      null,
      null,
      null,
      null,
      null,
      null,
      null,
      null,
      null,
      null,
      null,
      null,
      null,
      null,
      null,
      null,
      null,
      null,
      null,
      null,
      null,
      null,
      null,
      null,
      null,
      null,
      null,
      null,
      null,
      null,
      null,
      null,
      null,
      null,
      null,
      null,
      null,
      null,
      null,
      null,
      null,
      null,
      null,
      null,
      null,
      null,
      null,
      null,
      null,
      null,
      null,
      null,
      null,
      null,
      null,
      null,
      null,
      null,
      null,
      null,
      null,
      null,
      null,
      null,
      null,
      null,
      null,
      null,
      null,
      null,
      null,
      null,
      null,
      null,
      null,
      null,
      null,
      null,
      null,
      null,
      null,
      null,
      null,
      null,
      null,
      null,
      null,
      null,
      null,
      null,
      null,
      null,
      null,
      null,
      null,
      null,
      null,
      null,
      null,
      null,
      null,
      null,
      null,
      null,
      null,
      null,
      null,
      null,
      null,
      null,
      null,
      null,
      null,
      null,
      null,
      null,
      null,
      null,
      null,
      null,
      null,
      null,
      null,
      null,
      null,
      null,
      null,
      null,
      null,
      null,
      null,
      null
    ],
    "tn": [
      null,
      null,
      null,
      null,
      null,
      null,
      null,
      null,
      null,
      null,
      null,
      null,
      null,
      null,
      null,
      null,
      null,
      null,
      null,
      null,
      null,
      null,
      null,
      null,
      null,
      null,
      null,
      null,
      null,
      null,
      null,
      null,
      null,
      null,
      null,
      null,
      null,
      null,
      null,
      null,
      null,
      null,
      null,
      null,
      null,
      null,
      null,
      null,
      null,
      null,
      null,
      null,
      null,
      null,
      null,
      null,
      null,
      null,
      null,
      null,
      null,
      null,
      null,
      null,
      null,
      null,
      null,
      null,
      null,
      null,
      null,
      null,
      null,
      null,
      null,
      null,
      null,
      null,
      null,
      null,
      null,
      null,
      null,
      null,
      null,
      null,
      null,
      null,
      null,
      null,
      null,
      null,
      null,
      null,
      null,
      null,
      null,
      null,
      null,
      null,
      null,
      null,
      null,
      null,
      null,
      null,
      null,
      null,
      null,
      null,
      null,
      null,
      null,
      null,
      null,
      null,
      null,
      null,
      null,
      null,
      null,
      null,
      null,
      null,
      null,
      null,
      null,
      null,
      null,
      null,
      null,
      null,
      null,
      null,
      null,
      null,
      null,
      null,
      null,
      null,
      null,
      null,
      null,
      null,
      null,
      null,
      null,
      null,
      null,
      null,
      null,
      null,
      null,
      null,
      null,
      null,
      null,
      null,
      null,
      null,
      null,
      null,
      null,
      null,
      null,
      null,
      null,
      null,
      null,
      null,
      null,
      null,
      null,
      null,
      null,
      null,
      null,
      null,
      null,
      null,
      null,
      null,
      null,
      null,
      null,
      null,
      null,
      null,
      null,
      null,
      null,
      null,
      null,
      null,
      null,
      null,
      null,
      null,
      null,
      null,
      null,
      null,
      null,
      null,
      null,
      null,
      null,
      null,
      null,
      null,
      null,
      null,
      null,
      null,
      null,
      null,
      null,
      null,
      null,
      null,
      null,
      null,
      null,
      null,
      null,
      null,
      null,
      null,
      null,
      null,
      null,
      null,
      null,
      null,
      null,
      null,
      null,
      null,
      null,
      null,
      null,
      null,
      null,
      null,
      null,
      null,
      2,
      98,
      74,
      54,
      6,
      5,
      13,
      -33,
      -37,
      -54,
      -82,
      18,
      -51,
      23,
      29,
      4,
      -7,
      24,
      -45,
      -65,
      7,
      -33,
      -41,
      -2,
      -16,
      8,
      -18,
      17,
      55,
      -36,
      -65,
      -82,
      -80,
      -86,
      -80,
      -92,
      -17,
      -120,
      -77,
      -154,
      -177,
      -128,
      -2,
      -24,
      -41,
      52,
      5,
      -3,
      -79,
      -45,
      -30,
      -56,
      -10,
      -70,
      -42,
      12,
      -1,
      -102,
      -89,
      -72,
      -34,
      16,
      38,
      7,
      2,
      15,
      82,
      52,
      53,
      51,
      52,
      25,
      -39,
      -65,
      -181,
      -192,
      -215,
      -187,
      -234,
      -232,
      -221,
      -191,
      -128,
      -64,
      -19,
      -158,
      -158,
      -124,
      -155,
      -145,
      -40,
      -65,
      -48,
      -44,
      -101,
      -27,
      25,
      -50,
      -43,
      -35,
      -76,
      -64,
      -107,
      -70,
      -53,
      -77,
      -82,
      -56,
      -65,
      -97,
      -31,
      -17,
      -40,
      -27,
      -30,
      -47,
      -152,
      -216,
      -212,
      -138,
      -96,
      -153,
      -203,
      -185,
      -140,
      -171,
      -207,
      -116,
      -27,
      16,
      15,
      -6,
      46,
      51,
      -12,
      -54,
      -27,
      -77,
      -19,
      -78,
      -56,
      -56,
      -38,
      -53,
      -49,
      -164,
      -164,
      -104,
      -92,
      -61,
      21,
      -14,
      4,
      -23,
      -21,
      -8,
      -11,
      -56,
      -9,
      53,
      -23,
      -40,
      -34,
      -72,
      -85,
      -89,
      -65,
      -39,
      -34,
      -27,
      -22,
      -9,
      -29,
      -18,
      -38,
      -46,
      -24,
      -5,
      -8,
      -22,
      -14,
      -29,
      -46,
      -68,
      -37,
      -98,
      -73,
      12,
      -7,
      -16,
      -7,
      8,
      13,
      19,
      43,
      36,
      35,
      32,
      5,
      10,
      -20,
      -26,
      22,
      1,
      -13,
      -40,
      -42,
      -59,
      -7,
      2,
      -8,
      -14,
      19,
      9,
      53,
      46,
      24,
      42,
      80,
      16,
      -7,
      -32,
      -20,
      -24,
      -14,
      -44,
      -41,
      -29,
      -49,
      -76,
      -55,
      -50,
      -61,
      -32,
      32,
      -1,
      28,
      25,
      16,
      31,
      1,
      19,
      78,
      74,
      35,
      60,
      44,
      15,
      5,
      -1,
      38,
      33,
      41,
      27,
      52,
      77,
      63,
      32,
      18,
      4,
      71,
      94,
      60,
      60,
      24,
      -1,
      66,
      62,
      52,
      29,
      37,
      17,
      6,
      34,
      13,
      5,
      -20,
      27,
      -8,
      -29,
      -2,
      38,
      38,
      -8,
      -8,
      70,
      75,
      88,
      88,
      83,
      88,
      90,
      84,
      80,
      90,
      76,
      88,
      73,
      51,
      45,
      36,
      43,
      84,
      83,
      66,
      47,
      -2,
      107,
      112,
      103,
      82,
      94,
      73,
      72,
      101,
      102,
      117,
      107,
      107,
      110,
      116,
      120,
      123,
      116,
      99,
      75,
      64,
      68,
      124,
      116,
      32,
      10,
      94,
      94,
      67,
      76,
      58,
      67,
      59,
      53,
      37,
      44,
      83,
      75,
      62,
      62,
      113,
      102,
      60,
      67,
      56,
      16,
      -4,
      85,
      106,
      90,
      82,
      87,
      92,
      90,
      86,
      81,
      85,
      88,
      75,
      67,
      57,
      35,
      42,
      71,
      47,
      38,
      55,
      49,
      13,
      56,
      41,
      -2,
      -47,
      2,
      -27,
      -26,
      11,
      40,
      81,
      74,
      67,
      67,
      35,
      -21,
      -24,
      73,
      66,
      63,
      6,
      -34,
      28,
      13,
      -19,
      -4,
      21,
      26,
      44,
      62,
      42,
      112,
      42,
      -6,
      13,
      -7,
      -34,
      -16,
      -56,
      -40,
      -85,
      -73,
      -94,
      -167,
      -183,
      -132,
      -182,
      -127,
      -121,
      44,
      21,
      6,
      -34,
      -47,
      -75,
      -76,
      -42,
      -33,
      -47,
      -124,
      -133,
      -105,
      -48,
      -61,
      -96,
      -132,
      -158,
      -106,
      -12,
      7,
      -32,
      -71,
      -70,
      -46,
      -8,
      -65,
      -110,
      -136,
      -61,
      null,
      null,
      null,
      null,
      null,
      null,
      null,
      null,
      null,
      null,
      null,
      -13,
      -77,
      -81,
      -103,
      -109,
      -135,
      -51,
      -88,
      -48,
      -29,
      -40,
      13,
      67,
      81,
      -11,
      -31,
      -1,
      -31,
      23,
      -74,
      -80,
      -141,
      -134,
      -84,
      -84,
      -180,
      -182,
      -97,
      -157,
      -155,
      -152,
      -33,
      -42,
      -136,
      -204,
      -6,
      -68,
      27,
      7,
      -54,
      -57,
      41,
      -8,
      -76,
      -90,
      -84,
      -46,
      -72,
      -100,
      -118,
      -130,
      -139,
      -65,
      -55,
      -90,
      -120,
      -69,
      -155,
      -101,
      -11,
      -140,
      -179,
      -191,
      -156,
      -198,
      -206,
      -141,
      -233,
      -242,
      -143,
      -146,
      -156,
      -136,
      -29,
      -78,
      -101,
      -63,
      -78,
      -64,
      -116,
      -81,
      -123,
      -19,
      -29,
      -13,
      -3,
      -15,
      -13,
      0,
      -20,
      -21,
      -15,
      -31,
      -20,
      -23,
      -16,
      -15,
      -2,
      -52,
      -50,
      -48,
      -59,
      -62,
      -93,
      -98,
      -35,
      -68,
      -1,
      -30,
      -24,
      -34,
      -1,
      -32,
      -79,
      -97,
      -55,
      48,
      18,
      14,
      -25,
      -40,
      -2,
      -15,
      -50,
      -14,
      3,
      16,
      -30,
      -55,
      1,
      -10,
      29,
      28,
      -5,
      -5,
      24,
      77,
      65,
      39,
      28,
      -59,
      -48,
      -24,
      -58,
      -16,
      -32,
      -46,
      -95,
      -52,
      -6,
      48,
      25,
      24,
      -26,
      43,
      54,
      -23,
      -26,
      36,
      1,
      -16,
      29,
      64,
      22,
      29,
      45,
      60,
      43,
      22,
      18,
      16,
      62,
      60,
      56,
      53,
      45,
      56,
      20,
      52,
      34,
      10,
      54,
      41,
      26,
      35,
      14,
      21,
      27,
      61,
      70,
      42,
      46,
      54,
      68,
      78,
      81,
      69,
      64,
      80,
      79,
      73,
      98,
      67,
      59,
      48,
      30,
      24,
      82,
      95,
      88,
      85,
      101,
      126,
      123,
      116,
      123,
      109,
      83,
      62,
      119,
      133,
      null,
      null,
      null,
      null,
      null,
      null,
      null,
      null,
      null,
      null,
      null,
      null,
      null,
      null,
      null,
      null,
      null,
      null,
      null,
      null,
      null,
      null,
      null,
      null,
      null,
      null,
      null,
      null,
      null,
      null,
      null,
      null,
      null,
      null,
      null,
      null,
      null,
      null,
      null,
      null,
      null,
      null,
      null,
      null,
      null,
      null,
      null,
      null,
      null,
      null,
      null,
      null,
      null,
      null,
      null,
      null,
      null,
      null,
      null,
      null,
      null,
      null,
      null,
      null,
      null,
      null,
      null,
      null,
      null,
      null,
      null,
      null,
      null,
      null,
      null,
      null,
      null,
      null,
      null,
      null,
      null,
      null,
      null,
      null,
      null,
      null,
      null,
      null,
      null,
      null,
      null,
      null,
      null,
      null,
      null,
      null,
      null,
      null,
      null,
      null,
      null,
      null,
      null,
      null,
      null,
      null,
      null,
      null,
      null,
      null,
      null,
      null,
      null,
      null,
      null,
      null,
      null,
      null,
      null,
      null,
      null,
      null,
      null,
      null,
      null,
      null,
      null,
      null,
      null,
      null,
      null,
      null,
      null,
      null,
      null,
      null,
      null,
      null,
      null,
      null,
      null,
      null,
      null,
      null,
      null,
      null,
      null,
      null,
      null,
      null,
      null,
      null,
      null,
      null,
      null,
      null,
      null,
      null,
      null,
      null,
      null,
      null,
      null,
      null
    ]
  }
}
